{
    "assets": [
        {
            "chunkNames": [
                "vendor"
            ],
            "chunks": [
                0
            ],
            "emitted": true,
            "name": "vendor.js",
            "size": 352999
        },
        {
            "chunkNames": [
                "app"
            ],
            "chunks": [
                1
            ],
            "emitted": true,
            "name": "app.js",
            "size": 53103
        },
        {
            "chunkNames": [
                "vendor"
            ],
            "chunks": [
                0
            ],
            "emitted": true,
            "name": "vendor.js.map",
            "size": 2624078
        },
        {
            "chunkNames": [
                "app"
            ],
            "chunks": [
                1
            ],
            "emitted": true,
            "name": "app.js.map",
            "size": 293255
        },
        {
            "chunkNames": [],
            "chunks": [],
            "name": "../../stats/webpack.json",
            "size": 0
        }
    ],
    "assetsByChunkName": {
        "app": [
            "app.js",
            "app.js.map"
        ],
        "vendor": [
            "vendor.js",
            "vendor.js.map"
        ]
    },
    "errors": [],
    "hash": "dac82e6fc9a424bc12da",
    "publicPath": "/build/",
    "version": "1.12.14",
    "warnings": []
}
